jupyterlab_gitplus/__init__.py
jupyterlab_gitplus/github_v3.py
jupyterlab_gitplus/handlers.py
jupyterlab_gitplus/requests.py
jupyterlab_gitplus/utils.py
jupyterlab_gitplus/__pycache__/__init__.cpython-38.pyc
jupyterlab_gitplus/__pycache__/github_v3.cpython-38.pyc
jupyterlab_gitplus/__pycache__/handlers.cpython-38.pyc
jupyterlab_gitplus/__pycache__/requests.cpython-38.pyc
jupyterlab_gitplus/__pycache__/utils.cpython-38.pyc
jupyterlab_gitplus/labextension/build_log.json
jupyterlab_gitplus/labextension/package.json
jupyterlab_gitplus/labextension/static/lib_api_client_js-lib_index_js.e10620e94483b439179e.js
jupyterlab_gitplus/labextension/static/lib_api_client_js-lib_index_js.e10620e94483b439179e.js.map
jupyterlab_gitplus/labextension/static/remoteEntry.77af111d36260d0b7b79.js
jupyterlab_gitplus/labextension/static/remoteEntry.77af111d36260d0b7b79.js.map
jupyterlab_gitplus/labextension/static/style.js
jupyterlab_gitplus/labextension/static/style_index_css.48e7da924f67cd8e80de.js
jupyterlab_gitplus/labextension/static/style_index_css.48e7da924f67cd8e80de.js.map
jupyterlab_gitplus/labextension/static/vendors-node_modules_axios_index_js.897327ef06531a9782de.js
jupyterlab_gitplus/labextension/static/vendors-node_modules_axios_index_js.897327ef06531a9782de.js.map
jupyterlab_gitplus/labextension/static/vendors-node_modules_css-loader_dist_runtime_api_js-node_modules_css-loader_dist_runtime_cssW-72eba1.1ac31d3bab95b2084ab4.js
jupyterlab_gitplus/labextension/static/vendors-node_modules_css-loader_dist_runtime_api_js-node_modules_css-loader_dist_runtime_cssW-72eba1.1ac31d3bab95b2084ab4.js.map
jupyterlab_gitplus-0.3.4.data/data/etc/jupyter/jupyter_notebook_config.d/jupyterlab_gitplus.json
jupyterlab_gitplus-0.3.4.data/data/etc/jupyter/jupyter_server_config.d/jupyterlab_gitplus.json
jupyterlab_gitplus-0.3.4.data/data/share/jupyter/labextensions/@reviewnb/jupyterlab_gitplus/build_log.json
jupyterlab_gitplus-0.3.4.dist-info/LICENSE
jupyterlab_gitplus-0.3.4.dist-info/METADATA
jupyterlab_gitplus-0.3.4.dist-info/WHEEL
jupyterlab_gitplus-0.3.4.dist-info/top_level.txt
jupyterlab_gitplus-0.3.4.dist-info/RECORD
