Metadata-Version: 2.1
Name: jupyterlab_gitplus
Version: 0.3.4
Summary: JupyterLab extension to create GitHub pull requests
Home-page: https://github.com/ReviewNB/jupyterlab-gitplus
Author: Amit Rathi
Author-email: amit@reviewnb.com
Keywords: github,jupyter,notebook,pull request,version control,git
Platform: Linux
Platform: Mac OS X
Platform: Windows
Requires-Python: >=3
License-File: LICENSE
Requires-Dist: jupyterlab
Requires-Dist: gitpython
Requires-Dist: requests
Requires-Dist: urllib3
Requires-Dist: jupyter-server <3,>=1.6
